geoserver/__init__.py
geoserver/catalog.py
geoserver/layer.py
geoserver/layergroup.py
geoserver/namespace.py
geoserver/resource.py
geoserver/security.py
geoserver/service.py
geoserver/settings.py
geoserver/store.py
geoserver/style.py
geoserver/support.py
geoserver/util.py
geoserver/workspace.py
geoserver_restconfig-2.0.14.dist-info/licenses/LICENSE.txt
geoserver_restconfig-2.0.14.dist-info/METADATA
geoserver_restconfig-2.0.14.dist-info/WHEEL
geoserver_restconfig-2.0.14.dist-info/top_level.txt
geoserver_restconfig-2.0.14.dist-info/RECORD
