Metadata-Version: 2.4
Name: geoserver-restconfig
Version: 2.0.14
Summary: GeoServer REST Configuration
Home-page: https://github.com/GeoNode/geoserver-restconfig
Author: David Winslow, Sebastian Benthall, Alessio Fabiani
Author-email: alessio.fabiani@gmail.com
License: MIT
Keywords: GeoServer REST Configuration
Classifier: Development Status :: 5 - Production/Stable
Classifier: Intended Audience :: Developers
Classifier: Intended Audience :: Science/Research
Classifier: License :: OSI Approved :: MIT License
Classifier: Operating System :: OS Independent
Classifier: Programming Language :: Python
Classifier: Topic :: Scientific/Engineering :: GIS
Classifier: Programming Language :: Python :: 3.8
License-File: LICENSE.txt
Requires-Dist: requests>=2.14.0
Requires-Dist: gisdata>=0.5.4
Requires-Dist: six>=1.12.0
Requires-Dist: future
Dynamic: author
Dynamic: author-email
Dynamic: classifier
Dynamic: description
Dynamic: home-page
Dynamic: keywords
Dynamic: license
Dynamic: license-file
Dynamic: requires-dist
Dynamic: summary
